tngparser/__init__.py
tngparser/naming.py
tngparser/parser.py
tngparser-0.0.1.dist-info/LICENSE
tngparser-0.0.1.dist-info/METADATA
tngparser-0.0.1.dist-info/WHEEL
tngparser-0.0.1.dist-info/top_level.txt
tngparser-0.0.1.dist-info/RECORD
