Metadata-Version: 2.1
Name: tngparser
Version: 0.0.1
Summary: TNG statement parser python package
Author: Hao Quan Tang
Author-email: tanghq33@outlook.com
Keywords: python,tng,financial,parser,ewallet
Classifier: Development Status :: 3 - Alpha
Classifier: Intended Audience :: Education
Classifier: Programming Language :: Python :: 2
Classifier: Programming Language :: Python :: 3
Classifier: Operating System :: MacOS :: MacOS X
Classifier: Operating System :: Microsoft :: Windows
License-File: LICENSE
Requires-Dist: camelot-py[base]
Requires-Dist: opencv-python
Requires-Dist: PyPDF2 <3.0
